booking_statistics/__init__.py
booking_statistics/counter.py
booking_count_statistics-0.2.dist-info/METADATA
booking_count_statistics-0.2.dist-info/WHEEL
booking_count_statistics-0.2.dist-info/top_level.txt
booking_count_statistics-0.2.dist-info/RECORD
